[{"URL":"https:\/\/www.mdmountainside.com\/mcdonalds-1","Meta Description":"I'm lovin' it","No. Duplicates":5.0,"Duplicate URL":"https:\/\/www.mdmountainside.com\/mcdonalds-4","Paginated":"No"},{"URL":null,"Meta Description":null,"No. Duplicates":null,"Duplicate URL":"https:\/\/www.mdmountainside.com\/mcdonalds-5","Paginated":"No"},{"URL":null,"Meta Description":null,"No. Duplicates":null,"Duplicate URL":"https:\/\/www.mdmountainside.com\/mcdonalds-6","Paginated":"No"},{"URL":null,"Meta Description":null,"No. Duplicates":null,"Duplicate URL":"https:\/\/www.mdmountainside.com\/mcdonalds-7","Paginated":"No"},{"URL":null,"Meta Description":null,"No. Duplicates":null,"Duplicate URL":"https:\/\/www.mdmountainside.com\/mcdonalds-8","Paginated":"No"},{"URL":"https:\/\/www.mdmountainside.com\/first-peoples-community-federal-credit-union-frostburg","Meta Description":"First Peoples Community Federal Credit Union","No. Duplicates":4.0,"Duplicate URL":"https:\/\/www.mdmountainside.com\/first-peoples-community-federal-credit-union-cresaptown","Paginated":"No"},{"URL":null,"Meta Description":null,"No. Duplicates":null,"Duplicate URL":"https:\/\/www.mdmountainside.com\/first-peoples-community-federal-credit-union-industrial-blvd","Paginated":"No"},{"URL":null,"Meta Description":null,"No. Duplicates":null,"Duplicate URL":"https:\/\/www.mdmountainside.com\/first-peoples-community-federal-credit-union-lonaconing","Paginated":"No"},{"URL":null,"Meta Description":null,"No. Duplicates":null,"Duplicate URL":"https:\/\/www.mdmountainside.com\/first-peoples-community-federal-credit-union-queen-city-drive","Paginated":"No"},{"URL":"https:\/\/www.mdmountainside.com\/sheetz-virginia-avenue","Meta Description":"Sheetz Convenience Store","No. Duplicates":5.0,"Duplicate URL":"https:\/\/www.mdmountainside.com\/sheetz-bedford-road","Paginated":"No"},{"URL":null,"Meta Description":null,"No. Duplicates":null,"Duplicate URL":"https:\/\/www.mdmountainside.com\/sheetz-corriganville","Paginated":"No"},{"URL":null,"Meta Description":null,"No. Duplicates":null,"Duplicate URL":"https:\/\/www.mdmountainside.com\/sheetz-cresaptown","Paginated":"No"},{"URL":null,"Meta Description":null,"No. Duplicates":null,"Duplicate URL":"https:\/\/www.mdmountainside.com\/sheetz-frostburg","Paginated":"No"},{"URL":null,"Meta Description":null,"No. Duplicates":null,"Duplicate URL":"https:\/\/www.mdmountainside.com\/sheetz-winchester-road","Paginated":"Yes"},{"URL":"https:\/\/www.mdmountainside.com\/Delfest","Meta Description":"Expand your experience when you attend DelFest, Allegany County's premier music festival, featuring the legendary music of Del McCoury and family along with nationally touring bluegrass acts.","No. Duplicates":1.0,"Duplicate URL":"https:\/\/www.mdmountainside.com\/delfest","Paginated":"No"},{"URL":"https:\/\/www.mdmountainside.com\/mcdonalds-3","Meta Description":"I'm Lovin' It","No. Duplicates":1.0,"Duplicate URL":"https:\/\/www.mdmountainside.com\/mcdonalds-2","Paginated":"No"},{"URL":"https:\/\/www.mdmountainside.com\/jolly-roger-discount-liquors","Meta Description":"Beer, wine, and spirits.","No. Duplicates":1.0,"Duplicate URL":"https:\/\/www.mdmountainside.com\/allegany-liquor-store","Paginated":"No"},{"URL":"https:\/\/www.mdmountainside.com\/mt-bank-frostburg-2","Meta Description":"At M&T Bank, we've built our business on a tradition of reliability, accuracy and responsiveness to the needs of our customers.","No. Duplicates":3.0,"Duplicate URL":"https:\/\/www.mdmountainside.com\/mt-bank-lavale","Paginated":"No"},{"URL":null,"Meta Description":null,"No. Duplicates":null,"Duplicate URL":"https:\/\/www.mdmountainside.com\/mt-bank-south-cumberland","Paginated":"No"},{"URL":null,"Meta Description":null,"No. Duplicates":null,"Duplicate URL":"https:\/\/www.mdmountainside.com\/mt-bank-westernport","Paginated":"No"}]